Heisler/Heisler.py
Heisler/__init__.py
Heisler/data/Center_Temp_Cylinder.png
Heisler/data/Center_Temp_Sphere.png
Heisler/data/Center_Temp_Wall.png
Heisler/data/Internal_Energy_Cylinder.png
Heisler/data/Internal_Energy_Sphere.png
Heisler/data/Internal_Energy_Wall.png
Heisler/data/Temp_Dist_Cylinder.png
Heisler/data/Temp_Dist_Sphere.png
Heisler/data/Temp_Dist_Wall.png
tests/__init__.py
tests/test_heisler.py
Heisler-0.1.1.dist-info/LICENSE.txt
Heisler-0.1.1.dist-info/METADATA
Heisler-0.1.1.dist-info/WHEEL
Heisler-0.1.1.dist-info/top_level.txt
Heisler-0.1.1.dist-info/RECORD
