Metadata-Version: 2.1
Name: Heisler
Version: 0.1.1
Summary: A guide for using Heisler charts                and approximation for transient heat transfer.
Home-page: https://github.com/MRezaSadeghi/Heisler
Author: Reza Sadeghi
Author-email: lambertmech@gmail.com
Maintainer: Reza Sadeghi
License: Apache-2.0
Keywords: Heisler,Heat transfer
Platform: UNKNOWN
Classifier: License :: OSI Approved :: Apache Software License
Classifier: Operating System :: OS Independent
Classifier: Topic :: Scientific/Engineering
Classifier: Topic :: Scientific/Engineering :: Visualization
Classifier: Programming Language :: Python :: 3.6
Classifier: Programming Language :: Python :: 3.7
Classifier: Programming Language :: Python :: 3.8
Classifier: Programming Language :: Python :: 3.9
Requires-Python: >=3.6, <4
Requires-Dist: numpy
Requires-Dist: matplotlib
